.gitignore
.gitmodules
LICENSE
Makefile
README.md
mkdocs.yml
requirements.txt
rules.mk
setup.py
boringmindmachine/BoringKeymaker.py
boringmindmachine/BoringSheep.py
boringmindmachine/BoringShepherd.py
boringmindmachine/__init__.py
boringmindmachine/apikeys.example.py
boringmindmachine.egg-info/PKG-INFO
boringmindmachine.egg-info/SOURCES.txt
boringmindmachine.egg-info/dependency_links.txt
boringmindmachine.egg-info/not-zip-safe
boringmindmachine.egg-info/requires.txt
boringmindmachine.egg-info/top_level.txt
docs/index.md
docs/css/custom.css
tests/Readme.md
tests/__init__.py
tests/memo
tests/test_keymaker.py
tests/utils.py