Metadata-Version: 1.0
Name: boringmindmachine
Version: 23
Summary: boring-mind-machine provides boring base classes for awesome bot flocks.
Home-page: https://pages.charlesreid1.com/boring-mind-machine
Author: charlesreid1
Author-email: charles@charlesreid1.com
License: MIT
Platform: UNKNOWN
